Metadata-Version: 2.1
Name: core-semantic-search-app
Version: 1.0.0
Summary: Semantic Search utils for the curator core project
Home-page: https://github.com/usnistgov/core_semantic_search_app
Author: NIST IT Lab
Author-email: itl_inquiries@nist.gov
Provides-Extra: sentence_transformers
License-File: LICENSE.md
